[
  {
    "total_time": 945.81, 
    "mean_len": 7.09, 
    "times": [
      68.37, 
      81.23, 
      77.06, 
      53.3, 
      61.17, 
      65.22, 
      90.64, 
      94.02, 
      57.07, 
      58.38, 
      54.83, 
      86.39, 
      34.3, 
      63.83
    ], 
    "lens": [
      8.58, 
      8.49, 
      8.54, 
      7.44, 
      7.17, 
      7.48, 
      6.23, 
      7.07, 
      7.31, 
      5.09, 
      7.69, 
      9.76, 
      4.49, 
      3.95
    ], 
    "total_len": 99.29, 
    "operation_time": 94.02
  }, 
  {
    "total_heading": [
      899.18, 
      51519.22
    ], 
    "headings": [
      41.64, 
      82.76, 
      90.15, 
      32.35, 
      30.5, 
      68.07, 
      141.17, 
      112.96, 
      39.32, 
      42.27, 
      29.01, 
      93.4, 
      5.46, 
      90.12
    ]
  }, 
  {
    "robot_count": 14
  }
]
