[
  {
    "total_time": 269.28, 
    "mean_len": 7.1, 
    "times": [
      45.3, 
      39.92, 
      47.03, 
      44.02, 
      36.32, 
      37.76, 
      18.93
    ], 
    "lens": [
      8.6, 
      7.58, 
      8.06, 
      8.39, 
      6.69, 
      6.81, 
      3.6
    ], 
    "total_len": 49.73, 
    "operation_time": 47.03
  }, 
  {
    "total_heading": [
      227.2, 
      13017.6
    ], 
    "headings": [
      49.06, 
      15.89, 
      30.06, 
      40.92, 
      20.09, 
      62.65, 
      8.53
    ]
  }, 
  {
    "n_robots": 7
  }
]
